<?xml version="1.0" encoding="utf-8"?>
<!DOCTYPE hibernate-mapping PUBLIC "-//Hibernate/Hibernate Mapping DTD 3.0//EN"
"http://hibernate.sourceforge.net/hibernate-mapping-3.0.dtd">
<!-- 
    Mapping file autogenerated by MyEclipse Persistence Tools
-->
<hibernate-mapping>
    <class name="net.xabc.oo.hr.entity.Rolerights" table="rolerights" catalog="hrdb">
        <id name="roleRightsId" type="java.lang.Integer">
            <column name="roleRights_id" />
            <generator class="native" />
        </id>
        <many-to-one name="rights" class="net.xabc.oo.hr.entity.Rights" fetch="select">
            <column name="roleRights_code" length="20" />
        </many-to-one>
        <many-to-one name="role" class="net.xabc.oo.hr.entity.Role" fetch="select">
            <column name="roleRights_role_Id" />
        </many-to-one>
    </class>
</hibernate-mapping>
